gp_flask_ext/__init__.py
gp_flask_ext/celery_events.py
gp_flask_ext/celery_nocodb.py
gp_flask_ext/celery_utils.py
gp_flask_ext/flask_celery.py
gp_flask_ext/flask_chatgpt.py
gp_flask_ext/flask_gitlab_oauth.py
gp_flask_ext/flask_logger.py
gp_flask_ext/flask_mqtt.py
gp_flask_ext/flask_nocodb.py
gp_flask_ext/flask_otp.py
gp_flask_ext/flask_protobuf.py
gp_flask_ext/flask_strapi.py
gp_flask_ext/mqtt.py
gp_flask_ext/nocodb.py
gp_flask_ext/protobuf.py
gp_flask_ext/strapi.py
gp_flask_ext/utils.py
gp_flask_ext/templates/base.html
gp_flask_ext/templates/detail-dialog.html
gp_flask_ext/templates/index.html
gp_flask_ext/templates/json-editor.html
gp_flask_ext/templates/table-with-pagination.html
gp_flask_ext/templates/celery/index.html
gp_flask_ext/templates/celery/inspect.html
gp_flask_ext/templates/celery/result.html
gp_flask_ext/templates/celery/upload.html
gp_flask_ext/templates/chatgpt/index.html
gp_flask_ext/templates/logger/index.html
gp_flask_ext/templates/mqtt/index.html
gp_flask_ext/templates/nocodb/index.html
gp_flask_ext/templates/otp/index.html
gp_flask_ext/templates/protobuf/index.html
gp_flask_ext-0.0.21.dist-info/AUTHORS
gp_flask_ext-0.0.21.dist-info/LICENSE
gp_flask_ext-0.0.21.dist-info/METADATA
gp_flask_ext-0.0.21.dist-info/WHEEL
gp_flask_ext-0.0.21.dist-info/pbr.json
gp_flask_ext-0.0.21.dist-info/top_level.txt
gp_flask_ext-0.0.21.dist-info/RECORD
