Metadata-Version: 2.1
Name: gp-flask-ext
Version: 0.0.21
Summary: flask extension for gp
Author: hil
Author-email: hil@carota.ai
License: MIT
Classifier: Programming Language :: Python :: 3
Classifier: Operating System :: OS Independent
License-File: LICENSE
License-File: AUTHORS
Requires-Dist: loguru
Requires-Dist: requests
Provides-Extra: full
Requires-Dist: loguru; extra == "full"
Requires-Dist: requests; extra == "full"
Requires-Dist: protobuf==3.13; extra == "full"
Requires-Dist: paho-mqtt==1.5; extra == "full"
Requires-Dist: flask_socketio==5.3.6; extra == "full"
Requires-Dist: celery; extra == "full"
Requires-Dist: pyotp; extra == "full"
Requires-Dist: openai; extra == "full"
